gninatorch/__init__.py
gninatorch/_version.py
gninatorch/dataloaders.py
gninatorch/gnina.py
gninatorch/inference.py
gninatorch/losses.py
gninatorch/metrics.py
gninatorch/models.py
gninatorch/setup.py
gninatorch/training.py
gninatorch/transforms.py
gninatorch/utils.py
gninatorch/data/intro
gninatorch/data/logo
gninatorch/weights/crossdock_default2018.pt
gninatorch/weights/crossdock_default2018_1.pt
gninatorch/weights/crossdock_default2018_2.pt
gninatorch/weights/crossdock_default2018_3.pt
gninatorch/weights/crossdock_default2018_4.pt
gninatorch/weights/default2017.pt
gninatorch/weights/dense.pt
gninatorch/weights/dense_1.pt
gninatorch/weights/dense_2.pt
gninatorch/weights/dense_3.pt
gninatorch/weights/dense_4.pt
gninatorch/weights/general_default2018.pt
gninatorch/weights/general_default2018_1.pt
gninatorch/weights/general_default2018_2.pt
gninatorch/weights/general_default2018_3.pt
gninatorch/weights/general_default2018_4.pt
gninatorch/weights/redock_default2018.pt
gninatorch/weights/redock_default2018_1.pt
gninatorch/weights/redock_default2018_2.pt
gninatorch/weights/redock_default2018_3.pt
gninatorch/weights/redock_default2018_4.pt
tests/__init__.py
tests/conftest.py
tests/test_dataloaders.py
tests/test_gnina.py
tests/test_import.py
tests/test_inference.py
tests/test_losses.py
tests/test_models.py
tests/test_setup.py
tests/test_training.py
tests/test_transforms.py
tests/test_utils.py
gninatorch-0.0.2.dist-info/LICENSE
gninatorch-0.0.2.dist-info/METADATA
gninatorch-0.0.2.dist-info/WHEEL
gninatorch-0.0.2.dist-info/top_level.txt
gninatorch-0.0.2.dist-info/RECORD
