Metadata-Version: 2.1
Name: gninatorch
Version: 0.0.2
Summary: PyTorch implementation of GNINA scoring function
Author: Rocco Meli
Author-email: rocco.meli@biodtp.ox.ac.uk
License: MIT
Platform: Linux
Requires-Python: >=3.7
License-File: LICENSE
Requires-Dist: torch
Requires-Dist: molgrid
Requires-Dist: numpy
